.pre-commit-config.yaml
LICENSE
README.md
pyproject.toml
.github/workflows/publish-to-test-pypi.yml
docs/calc_derivative.md
docs/calc_features.md
docs/calc_properties.md
docs/cluster_search.md
docs/mc.md
docs/regression.md
docs/sample_derivative.md
docs/tutorial-alloy.md
docs/tutorial-subs.md
examples/Ag-Au/fcc-primitive
examples/Ag-Au/pyclupan_derivatives_2.yaml
examples/Ag-Au/pyclupan_derivatives_3.yaml
examples/Ag-Au/pyclupan_derivatives_4.yaml
examples/Ag-Au/pyclupan_derivatives_5.yaml
examples/Ag-Au/pyclupan_derivatives_6.yaml
examples/Ag-Au/DFT/pyclupan_sample_attrs.yaml
examples/Ag-Au/DFT/2-0-0/POSCAR
examples/Ag-Au/DFT/2-0-0/poscar_pypolymlp
examples/Ag-Au/DFT/2-0-0/vasprun.xml
examples/Ag-Au/DFT/2-1-0/POSCAR
examples/Ag-Au/DFT/2-1-0/vasprun.xml
examples/Ag-Au/DFT/3-0-0/POSCAR
examples/Ag-Au/DFT/3-0-0/vasprun.xml
examples/Ag-Au/DFT/3-0-1/POSCAR
examples/Ag-Au/DFT/3-0-1/vasprun.xml
examples/Ag-Au/DFT/3-1-0/POSCAR
examples/Ag-Au/DFT/3-1-0/vasprun.xml
examples/Ag-Au/DFT/3-1-1/POSCAR
examples/Ag-Au/DFT/3-1-1/vasprun.xml
examples/Ag-Au/DFT/3-2-0/POSCAR
examples/Ag-Au/DFT/3-2-0/vasprun.xml
examples/Ag-Au/DFT/3-2-1/POSCAR
examples/Ag-Au/DFT/3-2-1/vasprun.xml
examples/Ag-Au/DFT/4-0-0/POSCAR
examples/Ag-Au/DFT/4-0-0/vasprun.xml
examples/Ag-Au/DFT/4-0-1/POSCAR
examples/Ag-Au/DFT/4-0-1/vasprun.xml
examples/Ag-Au/DFT/4-0-2/POSCAR
examples/Ag-Au/DFT/4-0-2/vasprun.xml
examples/Ag-Au/DFT/4-1-0/POSCAR
examples/Ag-Au/DFT/4-1-0/vasprun.xml
examples/Ag-Au/DFT/4-1-1/POSCAR
examples/Ag-Au/DFT/4-1-1/vasprun.xml
examples/Ag-Au/DFT/4-1-2/POSCAR
examples/Ag-Au/DFT/4-1-2/vasprun.xml
examples/Ag-Au/DFT/4-2-0/POSCAR
examples/Ag-Au/DFT/4-2-0/vasprun.xml
examples/Ag-Au/DFT/4-2-1/POSCAR
examples/Ag-Au/DFT/4-2-1/vasprun.xml
examples/Ag-Au/DFT/4-2-2/POSCAR
examples/Ag-Au/DFT/4-2-2/vasprun.xml
examples/Ag-Au/DFT/4-3-0/POSCAR
examples/Ag-Au/DFT/4-3-0/vasprun.xml
examples/Ag-Au/DFT/4-3-1/POSCAR
examples/Ag-Au/DFT/4-3-1/vasprun.xml
examples/Ag-Au/DFT/4-3-2/POSCAR
src/pyclupan.egg-info/PKG-INFO
src/pyclupan.egg-info/SOURCES.txt
src/pyclupan.egg-info/dependency_links.txt
src/pyclupan.egg-info/entry_points.txt
src/pyclupan.egg-info/requires.txt
src/pyclupan.egg-info/top_level.txt
