Metadata-Version: 2.4
Name: pyclupan
Version: 0.1.2.post0
Summary: This is the pyclupan module.
Author-email: Atsuto Seko <seko@cms.mtl.kyoto-u.ac.jp>
Maintainer-email: Atsuto Seko <seko@cms.mtl.kyoto-u.ac.jp>
License: BSD 3-Clause License
Project-URL: Homepage, https://github.com/sekocha/pyclupan
Project-URL: Repository, https://github.com/sekocha/pyclupan
Requires-Python: >=3.9
License-File: LICENSE
Requires-Dist: numpy!=2.0.*
Requires-Dist: scipy
Requires-Dist: scikit-learn
Requires-Dist: PyYAML>=5.3
Requires-Dist: setuptools>=61.0
Requires-Dist: spglib
Requires-Dist: phonopy
Requires-Dist: pypolymlp>=0.16.0
Provides-Extra: graphillion
Requires-Dist: graphillion; extra == "graphillion"
Provides-Extra: tools
Requires-Dist: graphillion; extra == "tools"
Dynamic: license-file
